libcloudspawner/__about__.py
libcloudspawner/__init__.py
libcloudspawner/spawner.py
libcloudspawner/data/example_userdata_from_scratch.yaml.j2
libcloudspawner/data/example_userdata_from_vanilla_cloudimage.yaml.j2
libcloudspawner/data/options_form.html.j2
libcloudspawner/data/userdata.sh.j2
libcloudspawner/manager/__init__.py
libcloudspawner/manager/errors.py
libcloudspawner/manager/nodemanager.py
libcloudspawner-2.3.3.dist-info/METADATA
libcloudspawner-2.3.3.dist-info/WHEEL
libcloudspawner-2.3.3.dist-info/licenses/AUTHORS
libcloudspawner-2.3.3.dist-info/licenses/LICENSE
libcloudspawner-2.3.3.dist-info/RECORD
