Metadata-Version: 2.1
Name: libcloudspawner
Version: 2.3.3
Summary: JupyterHub Spawner for clouds
Project-URL: Homepage, https://github.com/jupytercloud-project/jupyterhub-libcloudspawner
Project-URL: Documentation, https://libcloudspawner.readthedocs.io/en/latest/
Project-URL: Bug Tracker, https://github.com/jupytercloud-project/jupyterhub-libcloudspawner/issues
Author-email: Tristan Le Toullec <tristan.letoullec@cnrs.fr>
License-File: AUTHORS
License-File: LICENSE
Classifier: Development Status :: 5 - Production/Stable
Classifier: Intended Audience :: Science/Research
Classifier: License :: OSI Approved :: MIT License
Classifier: Operating System :: OS Independent
Classifier: Programming Language :: Python :: 3
Requires-Python: >=3.7
Requires-Dist: apache-libcloud
Requires-Dist: jinja2
Requires-Dist: jupyterhub>=4.0.0
